uvrepotemplate/__init__.py
uvrepotemplate/py.typed
uvrepotemplate-0.1.18.dist-info/METADATA
uvrepotemplate-0.1.18.dist-info/WHEEL
uvrepotemplate-0.1.18.dist-info/licenses/LICENSE
uvrepotemplate-0.1.18.dist-info/RECORD
