Metadata-Version: 2.4
Name: uvrepotemplate
Version: 0.1.18
Summary: Add your description here
Project-URL: Homepage, https://github.com/davidbrownell/uvRepoTemplate
Project-URL: Documentation, https://github.com/davidbrownell/uvRepoTemplate
Project-URL: Repository, https://github.com/davidbrownell/uvRepoTemplate
Author-email: David Brownell <github@davidbrownell.com>
License: MIT
License-File: LICENSE
Classifier: License :: OSI Approved :: MIT License
Classifier: Operating System :: MacOS
Classifier: Operating System :: Microsoft :: Windows
Classifier: Operating System :: POSIX :: Linux
Classifier: Programming Language :: Python
Classifier: Programming Language :: Python :: 3.10
Classifier: Programming Language :: Python :: 3.11
Classifier: Programming Language :: Python :: 3.12
Classifier: Programming Language :: Python :: 3.13
Requires-Python: >=3.10
